ndn/__init__.py
ndn/svs/__init__.py
ndn/svs/balancer.py
ndn/svs/core.py
ndn/svs/logger.py
ndn/svs/meta_data.py
ndn/svs/missing_data.py
ndn/svs/scheduler.py
ndn/svs/security.py
ndn/svs/state_table.py
ndn/svs/state_vector.py
ndn/svs/svs.py
ndn/svs/svs_base.py
ndn/svs/svs_base_thread.py
ndn/svs/svs_shared.py
ndn/svs/svs_shared_thread.py
ndn/svs/svs_thread.py
ndn/svs/tlv.py
ndn/svs/window.py
ndn_svs-0.3.17.dist-info/AUTHORS.rst
ndn_svs-0.3.17.dist-info/LICENSE.rst
ndn_svs-0.3.17.dist-info/METADATA
ndn_svs-0.3.17.dist-info/WHEEL
ndn_svs-0.3.17.dist-info/top_level.txt
ndn_svs-0.3.17.dist-info/RECORD
