Metadata-Version: 2.1
Name: ndn-svs
Version: 0.3.17
Summary: The NDN State Vector Sync (SVS) Protocol in Python 3
Home-page: https://github.com/justincpresley/ndn-python-svs
Download-URL: https://pypi.python.org/pypi/ndn-svs
Author: Justin C Presley
Author-email: justincpresley@gmail.com
Maintainer: Justin C Presley
Maintainer-email: justincpresley@gmail.com
License: LGPL-2.1 License
Project-URL: Bug Tracker, https://github.com/justincpresley/ndn-python-svs/issues
Project-URL: Source Code, https://github.com/justincpresley/ndn-python-svs
Keywords: NDN SVS
Platform: UNKNOWN
Classifier: Development Status :: 4 - Beta
Classifier: Intended Audience :: Developers
Classifier: Topic :: Software Development :: Libraries
Classifier: Topic :: Internet
Classifier: Topic :: System :: Networking
Classifier: License :: OSI Approved :: GNU Lesser General Public License v2 (LGPLv2)
Classifier: Programming Language :: Python :: 3.8
Classifier: Programming Language :: Python :: 3.9
Classifier: Programming Language :: Python :: 3.10
Requires-Python: >=3.8
License-File: LICENSE.rst
License-File: AUTHORS.rst
Requires-Dist: python-ndn (>=0.3)
Requires-Dist: ndn-storage (>=0.2.3)
Requires-Dist: pycryptodomex (>=3.14.1)
Requires-Dist: pytest (>=7.1.1)
Requires-Dist: Sphinx (>=4.4.0)
Requires-Dist: sphinx-autodoc-typehints (>=1.17.0)
Requires-Dist: sphinx-rtd-theme (>=1.0.0)
